morse_lab/__init__.py
morse_lab/morse.py
morse_lab/morse_dict.py
morse_lab-0.2.0.dist-info/LICENSE
morse_lab-0.2.0.dist-info/METADATA
morse_lab-0.2.0.dist-info/WHEEL
morse_lab-0.2.0.dist-info/top_level.txt
morse_lab-0.2.0.dist-info/RECORD
