Metadata-Version: 2.2
Name: morse_lab
Version: 0.2.0
Summary: A Python package for Morse code conversion, including Japanese support.
Home-page: https://github.com/rushiharkal1/morse_lab
Author: Rushikesh Sanjay Harkal
Author-email: rushiharkal1@outlook.com
Classifier: Programming Language :: Python :: 3
Classifier: License :: OSI Approved :: MIT License
Classifier: Operating System :: OS Independent
Requires-Python: >=3.7
License-File: LICENSE
Dynamic: author
Dynamic: author-email
Dynamic: classifier
Dynamic: description
Dynamic: description-content-type
Dynamic: home-page
Dynamic: requires-python
Dynamic: summary
